LICENSE
README.md
setup.py
birdcall/__init__.py
birdcall/birdcall.py
birdcall.egg-info/PKG-INFO
birdcall.egg-info/SOURCES.txt
birdcall.egg-info/dependency_links.txt
birdcall.egg-info/requires.txt
birdcall.egg-info/top_level.txt