Metadata-Version: 2.1
Name: birdcall
Version: 1.0.1
Summary: Module for serverless Twitter bots.
Home-page: https://github.com/lukehollenback/birdcall
Author: Luke Hollenback
Author-email: luke.hollenback+birdcall@gmail.com
License: Apache License 2.0
Platform: UNKNOWN
Requires-Python: >=3.8
License-File: LICENSE
